{
  "200": {
    "name": "Clement 10 Year Rhum Agricole",
    "notes": "",
    "slug": null,
    "status_seen": "no_match",
    "suggestions": [
      ""
    ],
    "unofficial": true
  },
  "202": {
    "name": "Appleton Estate 8 Reserve Rum",
    "notes": "",
    "slug": null,
    "status_seen": "no_match",
    "suggestions": [
      ""
    ],
    "unofficial": true
  },
  "203": {
    "name": "Cruzan Estate Diamond Black Strap Rum",
    "notes": "",
    "slug": null,
    "status_seen": "no_match",
    "suggestions": [
      ""
    ],
    "unofficial": true
  },
  "204": {
    "name": "Denizen Merchant's Reserve 8 Year Rum",
    "notes": "",
    "slug": null,
    "status_seen": "no_match",
    "suggestions": [
      ""
    ],
    "unofficial": true
  },
  "205": {
    "name": "Roaming Road Thailand 11 Year Rum",
    "notes": "",
    "slug": null,
    "status_seen": "no_match",
    "suggestions": [
      ""
    ],
    "unofficial": true
  },
  "206": {
    "name": "Smith & Cross Traditional Jamaica Rum",
    "notes": "",
    "slug": null,
    "status_seen": "no_match",
    "suggestions": [
      ""
    ],
    "unofficial": true
  },
  "224": {
    "name": "Clear Water Lorenz Cinnamon Rum",
    "notes": "",
    "slug": null,
    "status_seen": "no_match",
    "suggestions": [
      ""
    ],
    "unofficial": true
  },
  "313": {
    "name": "Light rum",
    "notes": "",
    "slug": null,
    "status_seen": "no_match",
    "suggestions": [
      ""
    ],
    "unofficial": true
  },
  "358": {
    "name": "White Rum",
    "notes": "",
    "slug": null,
    "status_seen": "no_match",
    "suggestions": [
      ""
    ],
    "unofficial": true
  },
  "533": {
    "name": "Spiced Rum",
    "notes": "",
    "slug": null,
    "status_seen": "no_match",
    "suggestions": [
      ""
    ],
    "unofficial": true
  },
  "534": {
    "name": "Jamaican Rum",
    "notes": "",
    "slug": null,
    "status_seen": "no_match",
    "suggestions": [
      ""
    ],
    "unofficial": true
  },
  "556": {
    "name": "Capi Cacha\u00e7a",
    "notes": "",
    "slug": null,
    "status_seen": "no_match",
    "suggestions": [
      ""
    ],
    "unofficial": true
  },
  "557": {
    "name": "El Dorado 15 Year Old Rum",
    "notes": "",
    "slug": null,
    "status_seen": "no_match",
    "suggestions": [
      ""
    ],
    "unofficial": true
  },
  "591": {
    "name": "Kuleana Agricole Rum",
    "notes": "",
    "slug": null,
    "status_seen": "no_match",
    "suggestions": [
      ""
    ],
    "unofficial": true
  },
  "606": {
    "name": "Avu\u00e1 Amburana Cacha\u00e7a",
    "notes": "",
    "slug": null,
    "status_seen": "no_match",
    "suggestions": [
      ""
    ],
    "unofficial": true
  },
  "610": {
    "name": "Doctor Bird Private Barrel Cask Strength Madeira Finish Rum (B&B Exclusive)",
    "notes": "",
    "slug": null,
    "status_seen": "no_match",
    "suggestions": [
      ""
    ],
    "unofficial": true
  },
  "615": {
    "name": "Saint Benevolence Clairin",
    "notes": "",
    "slug": null,
    "status_seen": "no_match",
    "suggestions": [
      ""
    ],
    "unofficial": true
  }
}